bdspackmanager/__init__.py
bdspackmanager/__main__.py
bdspackmanager/json_updater.py
bdspackmanager/main.py
bdspackmanager/manifest_parser.py
bdspackmanager/pack_handler.py
bdspackmanager/utils.py
bdspackmanager-1.1.3.dist-info/METADATA
bdspackmanager-1.1.3.dist-info/WHEEL
bdspackmanager-1.1.3.dist-info/RECORD
