Metadata-Version: 2.1
Name: bdspackmanager
Version: 1.1.3
Summary: Command-line tool designed for managing resource and behavior packs on a Minecraft Bedrock Dedicated Server (BDS)
Home-page: https://github.com/DJStompZone/bdspackmanager
Author: DJ Stomp
Author-email: 85457381+DJStompZone@users.noreply.github.com
Maintainer: DJ Stomp
Maintainer-email: 85457381+DJStompZone@users.noreply.github.com
Requires-Python: >=3.9,<4.0
Classifier: Programming Language :: Python :: 3
Classifier: Programming Language :: Python :: 3.9
Classifier: Programming Language :: Python :: 3.10
Classifier: Programming Language :: Python :: 3.11
Classifier: Programming Language :: Python :: 3.12
Classifier: Programming Language :: Python :: 3.13
Requires-Dist: python-dotenv (>=1.0.1,<2.0.0)
Project-URL: Repository, https://github.com/DJStompZone/bdspackmanager
